benchmark/__init__.py
benchmark/web3py_weth_events_benchmark.py
transpose/__init__.py
transpose/contract.py
transpose/sql/__init__.py
transpose/sql/calls.py
transpose/sql/events.py
transpose/sql/general.py
transpose/stream/__init__.py
transpose/stream/base.py
transpose/stream/call.py
transpose/stream/event.py
transpose/utils/__init__.py
transpose/utils/address.py
transpose/utils/decode.py
transpose/utils/exceptions.py
transpose/utils/request.py
transpose/utils/time.py
transpose_decoding_sdk-1.0.5.dist-info/LICENSE
transpose_decoding_sdk-1.0.5.dist-info/METADATA
transpose_decoding_sdk-1.0.5.dist-info/WHEEL
transpose_decoding_sdk-1.0.5.dist-info/top_level.txt
transpose_decoding_sdk-1.0.5.dist-info/RECORD
