Metadata-Version: 2.1
Name: transpose_decoding_sdk
Version: 1.0.5
Summary: The Transpose Decoding SDK is a Python package that makes decoding contract activity on EVM blockchains as simple as possible. Simply specify a contract address and ABI to start streaming historical or live activity across decoded logs, transactions, and traces.
Home-page: https://github.com/TransposeData/transpose-decoding-sdk
Author: Alex Langshur (alangshur)
Author-email: alex@transpose.io
License: MIT
Keywords: web3,defi,ethereum,transpose,polygon,goerli,abi,decode,event,log,traces,rpc,api
Classifier: Development Status :: 3 - Alpha
Classifier: Intended Audience :: Developers
Classifier: Intended Audience :: Information Technology
Classifier: License :: OSI Approved :: MIT License
Classifier: Natural Language :: English
Classifier: Topic :: Database
Classifier: Topic :: Utilities
Requires: wheel
License-File: LICENSE
Requires-Dist: eth-event
Requires-Dist: pip-chill
Requires-Dist: dateutils
Requires-Dist: web3
